yabs_cowsay.py
yabs_cowsay-0.0.4.dist-info/LICENSE.txt
yabs_cowsay-0.0.4.dist-info/METADATA
yabs_cowsay-0.0.4.dist-info/WHEEL
yabs_cowsay-0.0.4.dist-info/entry_points.txt
yabs_cowsay-0.0.4.dist-info/top_level.txt
yabs_cowsay-0.0.4.dist-info/RECORD
