Metadata-Version: 2.1
Name: yabs-cowsay
Version: 0.0.4
Summary: Add a 'cowsay' task to Yabs
Home-page: https://github.com/mar10/yabs-cowsay/
Author: Martin Wendt
Author-email: yabs@wwwendt.de
Maintainer: Martin Wendt
Maintainer-email: yabs@wwwendt.de
License: MIT
Keywords: yabs,yabs-plugin
Platform: UNKNOWN
Classifier: Development Status :: 3 - Alpha
Classifier: Environment :: Console
Classifier: Intended Audience :: Developers
Classifier: License :: OSI Approved :: MIT License
Classifier: Operating System :: OS Independent
Classifier: Programming Language :: Python
Classifier: Programming Language :: Python :: 3
Classifier: Programming Language :: Python :: 3.5
Classifier: Programming Language :: Python :: 3.6
Classifier: Programming Language :: Python :: 3.7
Classifier: Programming Language :: Python :: 3.8
Classifier: Topic :: Software Development :: Build Tools
Classifier: Topic :: System :: Installation/Setup
Classifier: Topic :: System :: Software Distribution
